myupdater/__init__.py
myupdater-0.1.0.dist-info/LICENSE
myupdater-0.1.0.dist-info/METADATA
myupdater-0.1.0.dist-info/WHEEL
myupdater-0.1.0.dist-info/RECORD
