Metadata-Version: 2.1
Name: myupdater
Version: 0.1.0
Summary: 
Author: tct123
Author-email: 42028373+tct123@users.noreply.github.com
Requires-Python: >=3.13,<4.0
Classifier: Programming Language :: Python :: 3
Requires-Dist: requests (>=2.32.3,<3.0.0)
